LICENSE
MANIFEST.in
README.md
requirements.txt
setup.cfg
setup.py
djassets/__init__.py
djassets/constants.py
djassets/context_processors.py
djassets/urls.py
djassets/webp.py
djassets.egg-info/PKG-INFO
djassets.egg-info/SOURCES.txt
djassets.egg-info/dependency_links.txt
djassets.egg-info/requires.txt
djassets.egg-info/top_level.txt
djassets/static/adminmodal.js
djassets/static/cellinput.js
djassets/static/clipboard.js
djassets/static/confirm.js
djassets/static/deleteaction.js
djassets/static/form-autocomplete.js
djassets/static/jquery.maskedinput.js
djassets/static/list.js
djassets/static/modal.js
djassets/static/monosubmit.js
djassets/static/newtabaction.js
djassets/static/no-image.jpg
djassets/static/pinned-collapse.js
djassets/static/previewqtip.js
djassets/static/range-slider.js
djassets/static/select-chained-box.js
djassets/static/taskprogress.js
djassets/static/autocomplete/ajax-loader.gif
djassets/static/autocomplete/autocomplete-ajax.gif
djassets/static/autocomplete/autocomplete.css
djassets/static/autocomplete/autocomplete.js
djassets/static/autocomplete/select-arrow.gif
djassets/static/css/indents.css
djassets/static/jquery/ajax-csrf.js
djassets/static/jquery/jquery.ba-bbq.js
djassets/templatetags/__init__.py
djassets/templatetags/static_img.py