Metadata-Version: 1.1
Name: djassets
Version: 0.0.11
Summary: Django run app
Home-page: https://github.com/pmaigutyak/djassets
Author: Paul Maigutyak
Author-email: pmaigutyak@gmail.com
License: MIT
Download-URL: https://github.com/pmaigutyak/djassets/archive/0.0.11.tar.gz
Platform: UNKNOWN
